[
null,
{"id":1,"list":[{"code":311,"indent":0,"parameters":[0,0,1,0,750,false]},{"code":0,"indent":0,"parameters":[]}],"name":"-150 HP","switchId":1,"trigger":0},
{"id":2,"list":[{"code":331,"indent":0,"parameters":[-1,1,0,1000,false]},{"code":0,"indent":0,"parameters":[]}],"name":"Reaper Self Harm","switchId":1,"trigger":0},
{"id":3,"list":[{"code":0,"indent":0,"parameters":[]}],"name":"Summon Angel","switchId":1,"trigger":0},
{"id":4,"list":[{"code":0,"indent":0,"parameters":[]}],"name":"","switchId":1,"trigger":0}
]